mock_aiverify_apigw/__init__.py
mock_aiverify_apigw/__main__.py
mock_aiverify_apigw/lib/__init__.py
mock_aiverify_apigw/lib/constants.py
mock_aiverify_apigw/lib/database.py
mock_aiverify_apigw/lib/file_utils.py
mock_aiverify_apigw/lib/filestore.py
mock_aiverify_apigw/lib/logging.py
mock_aiverify_apigw/lib/plugin_store.py
mock_aiverify_apigw/lib/s3.py
mock_aiverify_apigw/lib/schemas_utils.py
mock_aiverify_apigw/lib/syntax_checker.py
mock_aiverify_apigw/lib/utils.py
mock_aiverify_apigw/lib/validators.py
mock_aiverify_apigw/models/__init__.py
mock_aiverify_apigw/models/base_model.py
mock_aiverify_apigw/models/plugin_model.py
mock_aiverify_apigw/models/test_artifact_model.py
mock_aiverify_apigw/models/test_dataset_model.py
mock_aiverify_apigw/models/test_model_model.py
mock_aiverify_apigw/models/test_result_model.py
mock_aiverify_apigw/models/uploaded_file_model.py
mock_aiverify_apigw/models/user_group_model.py
mock_aiverify_apigw/models/user_model.py
mock_aiverify_apigw/routers/__init__.py
mock_aiverify_apigw/routers/test_result_router.py
mock_aiverify_apigw/schemas/__init__.py
mock_aiverify_apigw/schemas/algorithm.py
mock_aiverify_apigw/schemas/input_block.py
mock_aiverify_apigw/schemas/load_examples.py
mock_aiverify_apigw/schemas/plugin.py
mock_aiverify_apigw/schemas/template.py
mock_aiverify_apigw/schemas/test_result.py
mock_aiverify_apigw/schemas/widget.py
mock_aiverify_apigw/schemas/examples/test_result_examples.json
mock_aiverify_apigw-2.0.0a1.dist-info/METADATA
mock_aiverify_apigw-2.0.0a1.dist-info/WHEEL
mock_aiverify_apigw-2.0.0a1.dist-info/RECORD
