Metadata-Version: 2.3
Name: mock-aiverify-apigw
Version: 2.0.0a1
Summary: The apigw provides middleware functionality for the aiverify portal
Project-URL: Documentation, https://github.com/aiverify-foundation/aiverify/tree/v2.x#readme
Project-URL: Issues, https://github.com/aiverify-foundation/aiverify/issues
Project-URL: Source, https://github.com/aiverify-foundation/aiverify/tree/v2.x
Author-email: Peck Yoke <leong_peck_yoke@imda.gov.sg>
License-Expression: MIT
Classifier: Development Status :: 4 - Beta
Classifier: Programming Language :: Python :: 3
Classifier: Programming Language :: Python :: 3.11
Classifier: Programming Language :: Python :: 3.12
Classifier: Programming Language :: Python :: Implementation :: CPython
Classifier: Programming Language :: Python :: Implementation :: PyPy
Requires-Python: >=3.11
Requires-Dist: boto3>=1.35.6
Requires-Dist: fastapi[standard]>=0.112.0
Requires-Dist: jsonschema>=4.23.0
Requires-Dist: python-dotenv>=1.0.1
Requires-Dist: sqlalchemy>=2.0.32
